pynscontroller/__init__.py
py_ns_controller-0.2.2.dist-info/METADATA
py_ns_controller-0.2.2.dist-info/WHEEL
py_ns_controller-0.2.2.dist-info/top_level.txt
py_ns_controller-0.2.2.dist-info/RECORD
