Metadata-Version: 2.1
Name: py-ns-controller
Version: 0.2.2
Summary: Python Nintendo Switch controller simulator 
Home-page: https://github.com/shinyypig/pynscontroller
Author: shinyypig
Author-email: shinyypig@gmail.com
License: UNKNOWN
Platform: UNKNOWN
Classifier: Programming Language :: Python :: 3
Classifier: License :: OSI Approved :: MIT License
Classifier: Operating System :: OS Independent
